pptx2md/__init__.py
pptx2md/__main__.py
pptx2md/global_var.py
pptx2md/outputter.py
pptx2md/parser.py
pptx2md/tools.py
PPTX2MD2REVEALJS-1.0.0.dist-info/LICENSE
PPTX2MD2REVEALJS-1.0.0.dist-info/METADATA
PPTX2MD2REVEALJS-1.0.0.dist-info/WHEEL
PPTX2MD2REVEALJS-1.0.0.dist-info/top_level.txt
PPTX2MD2REVEALJS-1.0.0.dist-info/RECORD
