Metadata-Version: 2.1
Name: PPTX2MD2REVEALJS
Version: 1.0.0
Summary: Converts a pptx file to MD File.
Home-page: https://github.com/vijayk1981/pptx2md2reveal
Author: Vijay Kasibhatla
Author-email: vijay.kasibhatla@gmail.com
Classifier: License :: OSI Approved :: MIT License
Classifier: Programming Language :: Python :: 3.7
Requires-Python: >=3.6
License-File: LICENSE
